piped_zookeeper
